nkueamis/__init__.py
nkueamis/nkueamis.py
nkueamis-0.4.3.dist-info/DESCRIPTION.rst
nkueamis-0.4.3.dist-info/METADATA
nkueamis-0.4.3.dist-info/RECORD
nkueamis-0.4.3.dist-info/WHEEL
nkueamis-0.4.3.dist-info/entry_points.txt
nkueamis-0.4.3.dist-info/metadata.json
nkueamis-0.4.3.dist-info/top_level.txt
