Metadata-Version: 2.0
Name: nkueamis
Version: 0.4.3
Summary: A simple tool to help get information in NKU-EAMIS(NKU Education Affairs Management Information System).
Home-page: https://github.com/zawnpn/nkueamis
Author: Wanpeng Zhang
Author-email: zawnpn@gmail.com
License: MIT
Keywords: NKU,eamis,Education
Platform: UNKNOWN
Classifier: Development Status :: 4 - Beta
Classifier: Intended Audience :: Developers
Classifier: Topic :: Software Development :: Libraries
Classifier: License :: OSI Approved :: MIT License
Classifier: Programming Language :: Python :: 3
Classifier: Programming Language :: Python :: 3.3
Classifier: Programming Language :: Python :: 3.4
Classifier: Programming Language :: Python :: 3.5
Classifier: Programming Language :: Python :: 3.6
Requires-Dist: bs4
Requires-Dist: docopt
Requires-Dist: prettytable
Requires-Dist: requests
